fusion_solar_py/__init__.py
fusion_solar_py/client.py
fusion_solar_py/exceptions.py
huawei_fusionsolar-0.0.3.dist-info/LICENSE.txt
huawei_fusionsolar-0.0.3.dist-info/METADATA
huawei_fusionsolar-0.0.3.dist-info/WHEEL
huawei_fusionsolar-0.0.3.dist-info/top_level.txt
huawei_fusionsolar-0.0.3.dist-info/RECORD
